gtime/__init__.py
gtime/__main__.py
gtime/cli.py
gtime/cli_commands.py
gtime/core.py
gtime/data.py
gtime/render.py
gtime/search.py
gtime/storage.py
gtime/timecore.py
gtime-0.5.0.dist-info/licenses/LICENSE
gtime-0.5.0.dist-info/METADATA
gtime-0.5.0.dist-info/WHEEL
gtime-0.5.0.dist-info/entry_points.txt
gtime-0.5.0.dist-info/top_level.txt
gtime-0.5.0.dist-info/RECORD
