Metadata-Version: 2.4
Name: gtime
Version: 0.5.0
Summary: Global Time Utility (gtime) - A modern, colorful Python CLI utility for global time zone lookup, comparison, and management. It supports fuzzy search, favorites, city comparison, meeting time conversion, and a live/watch mode
Author-email: Savitoj Singh <savv@duck.com>
License: MIT
Project-URL: Homepage, https://github.com/savitojs/gtime
Project-URL: Repository, https://github.com/savitojs/gtime
Project-URL: Bug Tracker, https://github.com/savitojs/gtime/issues
Project-URL: Documentation, https://github.com/savitojs/gtime#readme
Keywords: time,timezone,cli,utility,global,world,clock
Classifier: Development Status :: 4 - Beta
Classifier: Intended Audience :: Developers
Classifier: Intended Audience :: System Administrators
Classifier: License :: OSI Approved :: MIT License
Classifier: Operating System :: OS Independent
Classifier: Programming Language :: Python :: 3
Classifier: Programming Language :: Python :: 3.9
Classifier: Programming Language :: Python :: 3.10
Classifier: Programming Language :: Python :: 3.11
Classifier: Programming Language :: Python :: 3.12
Classifier: Topic :: System :: Shells
Classifier: Topic :: Utilities
Classifier: Environment :: Console
Requires-Python: >=3.9
License-File: LICENSE
Requires-Dist: rich
Requires-Dist: python-dateutil
Requires-Dist: thefuzz
Provides-Extra: dev
Requires-Dist: pytest; extra == "dev"
Requires-Dist: pytz; extra == "dev"
Dynamic: license-file
